<language version="1.0">
  <text string="Error while importing the Backup! Is this a valid file?">¡Error al importar la Copia de Seguridad! ¿Es el archivo correcto?</text>
  <text string="Import failed!">¡Error al Importar!</text>
  <text string="Error while exporting the Backup!">¡Error al exportar la Copia de Seguridad!</text>
  <text string="Export failed!">¡Error al Exportar!</text>
  <text string="Error while exporting the backups!">¡Error al exportar las Copias de seguridad!</text>
  <text string="Backup cancelled">Copia de Seguridad cancelada</text>
  <text string="Reason: Nothing selected to backup. Select folders first.">Razón: No hay nada seleccionado. Selecciona primero las carpetas.</text>
  <text string="Couldn't backup this folder:">No se encuentra ninguna Copia de seguridad en esta carpeta:</text>
  <text string="Reason:">Razón:</text>
  <text string="Data:">Datos:</text>
  <text string="Backup completed!">¡Copia de seguridad completada!</text>
  <text string="Backup completed">Copia de seguridad completada</text>
  <text string="Could not get data for this plugin">No se encuentran datos sobre este plugin</text>
  <text string="Could not get data">No se ha podido obtener datos</text>
  <text string="Error: No downloads are available for this project. It is probably still under construction.">Error: No hay descargas disponibles de este proyecto. Es probable que aún esté en desarrollo.</text>
  <text string="no downloads available">no hay descargas disponibles</text>
  <text string="Error while loading plugins. Internet available?">Error cargando plugins. ¿Hay acceso a Internet?</text>
  <text string="An error occured while loading this data">A ocurrido un error cargando datos</text>
  <text string="The file you chose to download is not supported yet.">No se aceptan archivos del tipo elegido.</text>
  <text string="At this moment only .jar and .zip files are supported.">De momento solo se aceptan archivos .jar y .zip</text>
  <text string="Not supported">No aceptado</text>
  <text string="You are about to install">Estás a punto de instalar</text>
  <text string="Do you wish to continue?">¿Quieres continuar?</text>
  <text string="Continue?">¿Continuar?</text>
  <text string="installing plugin:">instalando plugin:</text>
  <text string="was installed succesfully">ha sido instalado correctamente</text>
  <text string="Plugin Installed">Plugin Instalado</text>
  <text string="couldn't be installed. You have to visit the project page in order to install it manually.">no se puede instalar. Si quieres puedes visitar la página del proyecto para instalar el plugin manualmente.</text>
  <text string="Plugin Installation failed">No se ha podido instalar el plugin</text>
  <text string="A restart is required in order for the changes to take effect. The GUI will now close itself">BukkitGUI se cerrará para que puedan ser aplicados los cambios</text>
  <text string="Restart required">Se necesita reiniciar</text>
  <text string="Downloading latest Bukkit version">Descargando la última versión de Bukkit</text>
  <text string="Downloading Bukkit build">Descargando la construcción de Bukkit</text>
  <text string="Ok">Ok</text>
  <text string="Cancel">Cancelar</text>
  <text string="Browse...">Buscar...</text>
  <text string="Compress backup to reduce disk usage.">Comprimir la Copia de Seguridad.</text>
  <text string="Folders to backup, separated by ;">Carpetas de la Copia de Seguridad, separadas por ;</text>
  <text string="Backup name:">Nombre:</text>
  <text string="Folder to store backup:">Carpeta de Destino:</text>
  <text string="Backup settings">Configuración de Copia de Seguridad</text>
  <text string="Select folders to backup">Selecciona las carpetas para crear la Copia de Seguridad</text>
  <text string="Select folder to store backup">Selecciona la carpeta de destino donde se guardará la Copia de Seguridad</text>
  <text string="The name must be at least 1 character long">El nombre debe tener al menos un carácter de longitud</text>
  <text string="You can only use the following characters: a-z ; 1-9 ; _ ; -">Solo se pueden usar los siguientes carácteres: A-Z ; a-z ; 1-9 ; _ ; -</text>
  <text string="You need to specify at least 1 directory">Es necesario seleccionar al menos una carpeta</text>
  <text string="You need to specify the destination directory">Es necesario seleccionar la carpeta de destino</text>
  <text string="Warning type:">Tipo de advertencia:</text>
  <text string="Time:">Hora:</text>
  <text string="Cause:">Causa:</text>
  <text string="Text:">Texto:</text>
  <text string="Solutions:">Soluciones:</text>
  <text string="Solution">Solución</text>
  <text string="Apply">Aplicar</text>
  <text string="ErrorDiagnose">Error de Diagnóstico</text>
  <text string="This isn't a valid solution.">Esto no es una solución válida.</text>
  <text string="Invalid solution">Solución incorrecta</text>
  <text string="E-mail (optional):">E-mail (opcional):</text>
  <text string="Message:">Descripción:</text>
  <text string="Send!">¡Enviar!</text>
  <text string="Send Feedback">Enviar Comentario</text>
  <text string="You cannot send empty messages!">¡No se puede enviar sin una descripción!</text>
  <text string="Can't send">No se puede enviar</text>
  <text string="Status:">Estado:</text>
  <text string="">
  </text>
  <text string="Downloading...">Descargando...</text>
  <text string="File Download">Descargando Archivo</text>
  <text string="Contacting server...">Contactando con el servidor...</text>
  <text string="Downloading:">Descargando:</text>
  <text string="Path:">Ruta:</text>
  <text string="Version:">Versión:</text>
  <text string="Author(s):">Autor:</text>
  <text string="Name:">Nombre:</text>
  <text string="Main namespace:">Nombre Original:</text>
  <text string="Softdepend:">Dependencias:</text>
  <text string="Command">Comando</text>
  <text string="Description">Descripción</text>
  <text string="Usage">Uso</text>
  <text string="Aliases">Alias</text>
  <text string="Permission">Permisos</text>
  <text string="View latest version">Ver última versión</text>
  <text string="Plugin details:">Detalles del Plugin:</text>
  <text string="Date">Fecha</text>
  <text string="Version">Versión</text>
  <text string="File">Archivo</text>
  <text string="Craftbukkit">CraftBukkit</text>
  <text string="Authors:">Autores:</text>
  <text string="Site:">Web:</text>
  <text string="Categories:">Categorías:</text>
  <text string="Close">Cerrar</text>
  <text string="Install Selected Version">Instalar Versión Seleccionada</text>
  <text string="Type">Tipo</text>
  <text string="Plugin information">Información del Plugin</text>
  <text string="No data for this plugin available">No hay datos disponibles sobre este plugin</text>
  <text string="no data available">do hay datos disponibles</text>
  <text string="Could not load plugin data for this plugin">No se han podido cargar los datos de este plugin</text>
  <text string="Could not load plugin">No se puede cargar datos del plugin</text>
  <text string="Website:">Página Web:</text>
  <text string="Install">Instalar</text>
  <text string="Language">Idioma</text>
  <text string="GUI Version">Versión de BukkitGUI</text>
  <text string="Translator">Traductor</text>
  <text string="Comment">Comentarios</text>
  <text string="Install languages....">Instalar Idiomas....</text>
  <text string="Installing language:">Instalando Idioma:</text>
  <text string="I have read and accept the">He leído y acepto</text>
  <text string="OK">OK</text>
  <text string="Accept license...">Aceptar Licencia...</text>
  <text string="Accept">Aceptar</text>
  <text string="value:">Valor:</text>
  <text string="Setting:">Configurar:</text>
  <text string="Server settings...">Configurar servidor...</text>
  <text string="The name of the task. Doesn't affect the working of the task.">El nombre de la tarea. No afecta al trabajo de la tarea.</text>
  <text string="server start">Iniciar servidor</text>
  <text string="server starting">Iniciando servidor</text>
  <text string="server stop">Detener servidor</text>
  <text string="server stopping">Deteniendo servidor</text>
  <text string="elapsed time">Tiempo transcurrido</text>
  <text string="current time">Tiempo actual</text>
  <text string="player join">Se conecta un jugador</text>
  <text string="player leave">Se desconecta un jugador</text>
  <text string="server empty">Al vaciarse el servidor</text>
  <text string="heartbeat fail">El servidor no responde</text>
  <text string="task finished">Tarea finalizada</text>
  <text string="Type:">Tipo:</text>
  <text string="Trigger">Evento</text>
  <text string="Explanation: Please select a type first">Descripción: Por favor selecciona primero un tipo de evento</text>
  <text string="parameters:">Parámetros:</text>
  <text string="Action">Acción</text>
  <text string="execute">Ejecutar</text>
  <text string="shellexecute">Ejecutar shell</text>
  <text string="command">Ejecutar un comando</text>
  <text string="stop server">Detener el servidor</text>
  <text string="start server">Iniciar el servidor</text>
  <text string="restart server">Reiniciar el servidor</text>
  <text string="restart server brute">Forzar el reinicio del servidor</text>
  <text string="backup">Realizar Copia de Seguridad</text>
  <text string="synchronize list">Sincronizar lista</text>
  <text string="Save">Guardar</text>
  <text string="Edit task...">Editar tarea...</text>
  <text string="Run this task when the server starts.">Ejecuta esta tarea después de iniciar el servidor.</text>
  <text string="No parameters required.">Se necesitan parámetros.</text>
  <text string="Run this task before the server starts.">Ejecuta esta tarea antes de iniciar el servidor.</text>
  <text string="Run this task when the server stops.">Ejecuta esta tarea después de detener el servidor.</text>
  <text string="Run this task before the server stops.">Ejecuta esta tarea antes de detener el servidor.</text>
  <text string="Run this task every hh:mm:ss while the server is running.">Ejecuta esta tarea cada hh:mm:ss si el servidor está funcionando.</text>
  <text string="The time in hh:mm:ss">El formato es hh:mm:ss</text>
  <text string="Run this task when the computer time is equal to hh:mm:ss.">Ejecuta esta tarea cuando la hora del PC marque las hh:mm:ss.</text>
  <text string="The time in hh:mm:ss. You can add multiple times, each in hh:mm:ss format, split by ;">El tiempo en hh:mm:ss. Puedes añadir múltiples horarios, con el formato hh:mm:ss, detenidos por ;</text>
  <text string="Run this task every time a player joins the server.">Ejecuta esta tarea cada vez que se conecta un jugador al servidor.</text>
  <text string="Optional: the player name(s) to trigger at, split by;">Opcional: puedes especificar el nombre del jugador/es, detenidos por ;</text>
  <text string="Run this task every time a player disconnects.">Ejecuta esta tarea cada vez que se desconecta un jugador del servidor.</text>
  <text string="Optional: the player name(s) to trigger at, split by ;">Opcional: puedes especificar el nombre del jugador/es, detenidos por ;</text>
  <text string="Run this task when a player disconnects and there are no longer players online.">Ejecuta esta tarea cuando el último jugador se desconecta.</text>
  <text string="Run this task when the server doesn't respond any longer. This task will send a heartbeat to the server, and check if the server responds">
    Ejecuta esta tarea cuando el servidor deja de responder. Esta tarea se enviará al corazón del servidor, para comprobar si el servidor responde
  </text>
  <text string="The amount of time between 2 heartbeats, in hh:mm:ss">Cantidad de tiempo entre dos respuestas del servidor, en hh:mm:ss</text>
  <text string="Run this task when another task finished. You can set an optional timeout.">Ejecuta esta tarea cuando otra tarea finalice. Puedes configurar un tiempo de espera opcional.</text>
  <text string="the name of the task. You can add a timeout, by adding the time in /hh:mm:ss format after the task name.">
    el nombre de la tarea. Puedes añadir un tiempo de espera, con el formato /hh:mm:ss después del nombre de la tarea.
  </text>
  <text string="Run a program, or a file that is associated with a default program.">Ejecuta un programa o archivo (asociado a un programa predeterminado).</text>
  <text string="the path to the program or file">la ruta del programa o archivo</text>
  <text string="Execute a CMD command.">Ejecuta un comando CMD.</text>
  <text string="the CMD command">el comando CMD</text>
  <text string="Send a command to the server, if the server is running.">Enviar un comando al servidor, si el servidor está funcionando.</text>
  <text string="the command to send. You can specify multiple commands, separated by ;">el comando a enviar. Puedes especificar múltiples comandos, detenidos con ;</text>
  <text string="Stop the server, if it's running.">Para el servidor, si esta funcionando.</text>
  <text string="No parameters required">No se necesitan parámetros</text>
  <text string="Start the server, if it isn't already running. No parameters required.">Inicia el servidor, si no esta funcionando. No se necesitan parámetros.</text>
  <text string="The server will start with the settings set in the superstart tab.">El servidor se iniciará con la configuración establecida en la pestaña Inicio.</text>
  <text string="Restart the server, if it's running. No parameters required.">Reinicia el servidor, si está funcionando. No se necesitan parámetros.</text>
  <text string="Restart a server that doesn't respond, by killing it and starting it again. Might cause data loss. USE WITH CAUTION.">
    Reinicia el servidor si no responde, será forzado y reiniciado. Puede causar la pérdida de datos. UTILIZAR CON PRECAUCIÓN.
  </text>
  <text string="Create a backup. Enter the name of the backup to execute.">Crear una Copia de Seguridad. Introduce el nombre de la Copia de Seguridad a ejecutar.</text>
  <text string="The name of the backup">El nombre de la Copia de Seguridad</text>
  <text string="Sycnhronize the GUI player list with the server player list">Sincroniza la lista de jugadores en BukkitGUI con la lista de jugadores del servidor.</text>
  <text string="Time should be in format hh:mm:ss">El formato es hh:mm:ss</text>
  <text string="You need to enter a command">Es necesario introducir un comando</text>
  <text string="You need to enter a file or program">Es necesario introducir un programa o archivo</text>
  <text string="You need to enter a backup name">Es necesario introducir un nombre para la Copia de Seguridad</text>
  <text string="You need to enter a valid backup name">Es necesario introducir un nombre de Copia de Seguridad válido</text>
  <text string="Explanation">Descripción</text>
  <text string="Parameters">Parámetros</text>
  <text string="You didn't enter valid values. Make sure all values are valid, and try again">No has introducido valores correctos. Comprueba los valores e inténtalo de nuevo</text>
  <text string="Save cancelled">Guardado cancelado</text>
  <text string="Send">Enviar</text>
  <text string="Don't Send">No enviar</text>
  <text string="Your comment (optional)">Tu comentario (opcional)</text>
  <text string="upload progress">subiendo en progreso</text>
  <text string="Email">Email</text>
  <text string="Your email (optional)">Tu e-mail (opcional)</text>
  <text string="Problem report">Informar del problema</text>
  <text string="Could not get ticket ID, upload cancelled. If you want to report this error manually, you can contact us at">
    No se ha podido obtener el ID del ticket, subida cancelada. Si quieres informar de este error, puedes contactar manualmente en
  </text>
  <text string="could not get ID">no se ha podido obtener la ID</text>
  <text string="This bug report can't be submitted automaticly: program outdated.">No se puede enviar este informe automáticamente: programa desactualizado.</text>
  <text string="Please make sure you have the latest version">Por favor asegúrate de tener la última versión</text>
  <text string="If you want to report this error manually, you can contact us at">Si quieres informar de este error manualmente, puedes contactar en</text>
  <text string="The log has been uploaded. Thank you for sending it towards us!">El log se ha cargado correctamente. ¡Gracias por enviarlo!</text>
  <text string="Your log ID is #">Tu nº de log ID es </text>
  <text string="You can keep this for future reference.">Puedes anotarlo para futuras referencias.</text>
  <text string="Log file sent!">¡Archivo Log enviado!</text>
  <text string="Error while importing the task! Is this a valid file?">¡Error importando las tareas! ¿Es un archivo correcto?</text>
  <text string="Error while exporting the task!">¡Error exportando la tarea!</text>
  <text string="Error while exporting the tasks!">¡Error exportando las tareas!</text>
  <text string="Install update">Instalar Actualización</text>
  <text string="Current version:">Versión actual:</text>
  <text string="Latest version:">Última versión:</text>
  <text string="An update is available. If you continue, this update will be installed automaticl">Hay una actualización disponible. Si continúas, se instalará automáticamente</text>
  <text string="y.">.</text>
  <text string="Note: if the server is running, it will be stopped while updating">Nota: si el servidor está funcionando, se detendrá para realizar la actualización</text>
  <text string="Release date:">Fecha de lanzamiento:</text>
  <text string="Updater">Actualizador The BukkitGUI</text>
  <text string="You have to accept in order to use the application. Do you want to exit?">Tienes que aceptar las condiciones para poder usar la aplicación. ¿Quieres salir?</text>
  <text string="Exit?">¿Salir?</text>
  <text string="Waiting for server to stop">Esperando que el servidor se detenga</text>
  <text string="Access to to the following folder was denied.">No se permite el acceso a la siguiente carpeta.</text>
  <text string="Please run this app as administrator to ensure proper working">Por favor ejecuta esta aplicación como administrador para asegurarte de que trabaja correctamente</text>
  <text string="Access to folder denied">Acceso a la carpeta denegado</text>
  <text string="Delete this plugin?">¿Borrar este plugin?</text>
  <text string="Delete plugin?">¿Borrar plugin?</text>
  <text string="You need to stop the server in order to remove this plugin. Stop server?">Es necesario detener el servidor para poder eliminar este plugin. ¿Detener servidor?</text>
  <text string="Server stop required">Necesario detener el servidor</text>
  <text string="It seems that this folder was created by the plugin:">Esta carpeta ha sido creada por el plugin:</text>
  <text string="Remove this folder?">¿Borrar esta carpeta?</text>
  <text string="Remove folder?">¿Borrar carpeta?</text>
  <text string="Plugin succesfully removed!">¡Plugin correctamente eliminado!</text>
  <text string="Succes!">¡Correcto!</text>
  <text string="Plugin removal failed. There might be some files left undeleted">Eliminación de plugin errónea. Pueden quedar algunos archivos sin borrar</text>
  <text string="Failed">Fallo</text>
  <text string="Failed to connect to remote server. Are the credentials correct?">No se ha podido conectar con el servidor remoto. ¿Las credenciales son correctas?</text>
  <text string="Failed to connect">Fallo al conectar</text>
  <text string="The java path could not be found, server start aborted">No se ha podido encontrar la ruta de java. Inicio del servidor detenido</text>
  <text string="Please select the correct java version in the superstart tab">Por favor selecciona la versión correcta de java en la pestaña Inicio</text>
  <text string="Could not start server">No se ha podido iniciar el servidor</text>
  <text string="Could not start the process - no executable given">No se ha podido iniciar el proceso - no se ha encontrado el ejecutable</text>
  <text string="The program couldn't find this executable: ">El programa no encuentra este ejecutable: </text>
  <text string="File not found">Archivo no encontrado</text>
  <text string="The server should be running before you can send commands.">El servidor debe estar funcionando para poder enviar comandos.</text>
  <text string="Could not send command">Comando no enviado</text>
  <text string="The command could not be sent due to an error. See the log file for more information">El comando no se ha podido enviar debido a un error. Consulta el archivo de registro para obtener más información</text>
  <text string="The GUI couldn't download data from">BukkitGUI no puede descargar datos de</text>
  <text string="The server didn't respond in time">El servidor no ha respondido a tiempo</text>
  <text string="Couldn't download data">No se han podido descargar los datos</text>
  <text string="The server is unavailable (Response code 503)">El servidor no está disponible (Código de respuesta 503)</text>
  <text string="The server is unavailable (Response code 502)">El servidor no está disponible (Código de respuesta 502)</text>
  <text string="The server didn't response in time">El servidor no ha respondido a tiempo</text>
  <text string="It seems that the server stopped responding. Do you want to kill the server?">Parece que el servidor no responde. ¿Quieres forzar el servidor?</text>
  <text string="Server not responding">El servidor no está respondiendo</text>
  <text string="The server is still running. Do you want to stop the server and exit the GUI?">El servidor está funcionando. ¿Quieres detener el servidor y salir de GUI?</text>
  <text string="Stop server?">¿Detener servidor?</text>
  <text string="The server could not be started: the .jar file specified could not be found. Please make sure all superstart settings are valid.">
    No se ha podido iniciar el servidor: el archivo .jar especificado no se encuentra. Por favor asegúrate de que esté bien configurado el Inicio.
  </text>
  <text string="Could't start server">No se ha podido iniciar el servidor</text>
  <text string="Starting bukkit server"> Iniciando servidor Bukkit</text>
  <text string="min. RAM:">RAM mínima:</text>
  <text string="max. RAM:">y RAM máxima:</text>
  <text string="Starting vanilla server"> Iniciando servidor Vanilla</text>
  <text string="Starting new remote jsonapi server...">Iniciando nuevo servidor remoto JSONAPI...</text>
  <text string="Starting java server"> Iniciando servidor Java</text>
  <text string="Retrieving your current bukkit version...">Obteniendo versión actual de Bukkit...</text>
  <text string="Your current bukkit version couldn't be determined">La versión actual de Bukkit no se puede determinar</text>
  <text string="Your current bukkit version is">Mí versión actual de Bukkit es</text>
  <text string="A new bukkit version is available:">Hay una nueva versión de Bukkit disponible:</text>
  <text string="A new version for bukkit is available:">Una nueva versión para Bukkit está disponible::</text>
  <text string="Bukkit was updated to the latest version:">Bukkit ha sido actualizado a la versión:</text>
  <text string="Do you really want to kill the server? This can corrupt your data!">¿Seguro que quieres forzar el servidor? ¡Se pueden dañar los datos!</text>
  <text string="Kill server?">¿Forzar servidor?</text>
  <text string="Starting server">Iniciando servidor</text>
  <text string="Server started">Servidor iniciado</text>
  <text string="Server running">Servidor Funcionando</text>
  <text string="Connected to remote server">Conectado al servidor remoto</text>
  <text string="Stop">Detener</text>
  <text string="Disconnect">Desconectar</text>
  <text string="Server stopped">Servidor detenido</text>
  <text string="Start">Iniciar</text>
  <text string="The server has stopped...">...el servidor ha sido detenido</text>
  <text string="Killed remote server connection, severe error in remote reader thread. Please report this bug.">Error grave en la lectura de los datos del servidor remoto, se ha perdido la conexión con el servidor remoto. Por favor informa sobre este bug.</text>
  <text string="The server could not be started, reason:">El servidor no puede ser iniciado, razón:</text>
  <text string="This is probably caused by another server that is running already.">Esto se debe a que otro servidor ya se está ejecutando actualmente.</text>
  <text string="Kill all java instances, and retry to start this server?">¿Detener todos los plugins e intentar iniciar el servidor?</text>
  <text string="Server couldn't be started">El servidor no puede ser iniciado</text>
  <text string="Player joined">Jugador conectado</text>
  <text string="logged in to the server">identificado en el servidor</text>
  <text string="at world">en el mundo</text>
  <text string="Player disconnected (Leave)">Jugador desconectado (Sale)</text>
  <text string="disconnected">desconectado</text>
  <text string="reason:">reason:</text>
  <text string="Player disconnected (Kick)">Jugador desconectado (Kikeado)</text>
  <text string="Player disconnected (Ban)">Jugador desconectado (Baneado)</text>
  <text string="Warning">Advertencia</text>
  <text string="Severe">Grave</text>
  <text string="status">Estado</text>
  <text string="Time since start:">Tiempo en funcionamiento:</text>
  <text string="Latest stable:">Última estable:</text>
  <text string="Latest beta:">Última beta:</text>
  <text string="Latest dev:">Última en desarrollo:</text>
  <text string="Bukkit version">Versión de Bukkit</text>
  <text string="Your current bukkit version could not be determined">No se puede determinar tu versión de Bukkit</text>
  <text string="The server settings you entered are invalid">La configuración del servidor introducida no es correcta</text>
  <text string="Invalid server settings">Configuración del servidor incorrecta</text>
  <text string="You must enter a path to the .jar file">Debes introducir la ruta del archivo .jar</text>
  <text string="Invalid file path, must be a .jar file">Ruta del archivo incorrecta, debe ser un archivo .jar</text>
  <text string="File doesn't exist!">¡El archivo no existe!</text>
  <text string="You can't use more then 1024MB RAM with Java x32">No puedes usar más de 1024MB de RAM con Java x32</text>
  <text string="locating...">localizando...</text>
  <text string="from">de</text>
  <text string="at">en</text>
  <text string="Error while loading plugins. Probably the server could not be reached.">Error durante la carga de plugins. Probablemente el servidor no ha podido obtenerlos.</text>
  <text string="You can right click and try refreshing.">Puedes intentar actualizar la lista de plugins, clicando en el botón derecho del ratón.</text>
  <text string="If you selected a category, it's possible that this category is empty.">Si has seleccionado una categoría, es posible que esta esté vacía.</text>
  <text string="Loaded">Se han cargado</text>
  <text string="plugins">plugins</text>
  <text string="Right click for options, double click for details.">Doble clic para ver los detalles, clic derecho para opciones.</text>
  <text string="No information available">No hay información disponible</text>
  <text string="Double click for more information. Right Click for options.">Doble clic para ver los detalles, clic derecho para opciones.</text>
  <text string="Copyright:">Copyright:</text>
  <text string="Web:">Web:</text>
  <text string="Computer name:">Nombre del PC:</text>
  <text string="CPU:">CPU:</text>
  <text string="RAM:">RAM:</text>
  <text string="OS:">SO:</text>
  <text string="Local IP:">IP Privada:</text>
  <text string="Ext. IP:">IP Pública:</text>
  <text string="You changed the language to ">Has cambiado al idioma </text>
  <text string="Restart the GUI for the changes to take effect">Reinicia BukkitGUI para que se apliquen los cambios</text>
  <text string="Do you really want to reset all GUI settings?">¿Realmente quieres restaurar la opciones de BukkitGUI?</text>
  <text string="Reset settings">Restaurar configuración</text>
  <text string="All settings will be resetted. You need to restart the GUI in order for the changes to take effect">La configuración se ha restaurado. Necesitas reiniciar BukkitGUI para que se apliquen los cambios</text>
  <text string="Autostart is currently disabled. Do you want to enable autostart?">AutoInicio está actualmente desactivado. ¿Quieres activar el AutoInicio?</text>
  <text string="Autostart disabled">AutoInicio desactivado</text>
  <text string="Autostart is currently enabled. Do you want to disable autostart?">AutoInicio está actualmente activado. ¿Quieres desactivar el AutoInicio?</text>
  <text string="Can't access autostart functions! Are you running this as administrator?">¡No es posible acceder a las funciones del AutoInicio! ¿Estás ejecutando como administrador?</text>
  <text string="Can't access autostart">Sin acceso al AutoInicio</text>
  <text string="General">Principal</text>
  <text string="Auto Scroll">Desplazamiento Automático</text>
  <text string="Say (Ctrl+S)">Chatear</text>
  <text string="Name">Nombre</text>
  <text string="Op">Poner OP</text>
  <text string="De-op">Quitar OP</text>
  <text string="Kick">Kikear</text>
  <text string="Ban">Banear</text>
  <text string="Gamemode">Modo de Juego</text>
  <text string="Survival">Superviviente</text>
  <text string="Creative">Creativo</text>
  <text string="Give...">Dar al jugador...</text>
  <text string="Refresh list">Actualizar lista</text>
  <text string="player_face.png">player_face.png</text>
  <text string="Info">Herramientas</text>
  <text string="000% [0000MB]">000% [0000Mb]</text>
  <text string="000%">000%</text>
  <text string="Total RAM Usage:">Uso total de la RAM:</text>
  <text string="Server RAM Usage:">Uso de RAM Servidor:</text>
  <text string="GUI RAM Usage:">Uso de RAM GUI:</text>
  <text string="Total CPU Usage:">Uso total de la CPU:</text>
  <text string="Server CPU Usage:">Uso de CPU Servidor:</text>
  <text string="GUI CPU Usage:">Uso de CPU GUI:</text>
  <text string="test">probar</text>
  <text string="Kill">Forzar</text>
  <text string="Reload">Recargar</text>
  <text string="Restart">Reiniciar</text>
  <text string="Players">Jugadores</text>
  <text string="View:">Ver:</text>
  <text string="IP">IP</text>
  <text string="Location">Localización</text>
  <text string="Time Joined">Conectado</text>
  <text string="Whitelisted">Autorizado</text>
  <text string="OP">OP</text>
  <text string="SuperStart">Inicio</text>
  <text string="Launch Server">Antes de "INICIAR el SERVIDOR" comprueba que no esté ya funcionando</text>
  <text string="Maintainance">Mantenimiento</text>
  <text string="Get current version #">Mostrar Versión Actual</text>
  <text string="Retrieve the current version on server start">Comprobar actualizaciones al iniciar BukkitGUI</text>
  <text string="Notify me when a server update is available">Notificarme cuando exista una actualización</text>
  <text string="Download build #">Descargar la construcción nº:</text>
  <text string="Download">Descargar</text>
  <text string="Download Latest Development Build">Descargar la Última Versión en Desarrollo</text>
  <text string="Download Latest Bèta Build">Descargar la Última Versión Beta</text>
  <text string="Download Latest Recommended Build">Descargar la Última Versión Recomendada</text>
  <text string="Remote Server">Configuración del Servidor Remoto</text>
  <text string="salt:">salt:</text>
  <text string="port:">puerto:</text>
  <text string="password:">contraseña:</text>
  <text string="username:">usuario:</text>
  <text string="host:">host:</text>
  <text string="Java Server">Configuración del Servidor Java</text>
  <text string="Custom switches:">Opciones:</text>
  <text string="...">...</text>
  <text string="Custom arguments:">Argumentos:</text>
  <text string="JAR file:">Archivo .jar:</text>
  <text string="Max. RAM:">RAM Máxima </text>
  <text string="Min. RAM:">RAM Mínima </text>
  <text string="Java Version:">Versión de Java:</text>
  <text string="Jre6x32">Java 6 (32 bits)</text>
  <text string="Jre6x64">Java 6 (64 bits)</text>
  <text string="Jre7x32">Java 7 (32 bits)</text>
  <text string="Jre7x64">Java 7 (64 bits)*</text>
  <text string="alternative java path">Java alternativo</text>
  <text string="Bukkit">Bukkit</text>
  <text string="Vanilla">Vanilla</text>
  <text string="Remote JSONAPI">Remoto JSONAPI</text>
  <text string="Generic Java">Java (Genérico)</text>
  <text string="Server Type:">Tipo de Servidor:</text>
  <text string="Error Logging">Log de Errores</text>
  <text string="Hide stacktraces from server output">Ocultar stacktraces del servidor</text>
  <text string="Hide errors from server output">Ocultar errores del servidor</text>
  <text string="Hide warnings from server output">Ocultar advertencias del servidor</text>
  <text string="Details...">Detalles...</text>
  <text string="ID">ID</text>
  <text string="Time">Hora</text>
  <text string="Text">Texto</text>
  <text string="error.png">error.png</text>
  <text string="exclamation.png">exclamation.png</text>
  <text string="Task manager">Programador</text>
  <text string="Import...">Importar...</text>
  <text string="Export...">Exportar...</text>
  <text string="Add...">Añadir...</text>
  <text string="Edit...">Editar...</text>
  <text string="Trigger Type">Evento</text>
  <text string="Trigger Parameters">Parámetros del Evento</text>
  <text string="Action type">Acción</text>
  <text string="Action parameters">Parámetros de Acción</text>
  <text string="Remove">Eliminar</text>
  <text string="Plugins">Plugins</text>
  <text string="Install Plugins">Instalar Plugins</text>
  <text string="Category:">Categoría:</text>
  <text string="Filter:">Filtro:</text>
  <text string="More info">Más información</text>
  <text string="Install plugin">Instalar plugin</text>
  <text string="Go to project page">Ir a la página del proyecto</text>
  <text string="Installed Plugins">Plugins Instalados</text>
  <text string="Author(s)">Autor/es</text>
  <text string="View versions">Mostrar versiones</text>
  <text string="Update">Actualizar</text>
  <text string="Project page...">Página del proyecto...</text>
  <text string="information.png">information.png</text>
  <text string="group.png">group.png</text>
  <text string="control_play.png">control_play.png</text>
  <text string="plugin.png">plugin.png</text>
  <text string="settings.png">settings.png</text>
  <text string="save.png">save.png</text>
  <text string="drive-download.png">drive-download.png</text>
  <text string="clock.png">clock.png</text>
  <text string="wrench.png">wrench.png</text>
  <text string="Drive-Backup-icon.png">Drive-Backup-icon.png</text>
  <text string="arrow_down.png">arrow_down.png</text>
  <text string="plugin_add.png">plugin_add.png</text>
  <text string="plugin_edit.png">plugin_edit.png</text>
  <text string="Server options">Propiedades</text>
  <text string="Right-click to see all available actions">Clic derecho para ver todas las acciones disponibles.</text>
  <text string="Add">Pon</text>
  <text string="Banned IPs">IPs Baneadas</text>
  <text string="Refresh">Actualizar</text>
  <text string="Banned Players">Jugadores Baneados</text>
  <text string="OPs">Jugadores OP</text>
  <text string="Whitelist">Autorizados</text>
  <text string="Value">Valor</text>
  <text string="Backup">Copias de Seguridad</text>
  <text string="Execute">Ejecutar</text>
  <text string="Folders">Carpetas</text>
  <text string="Destination">Destino</text>
  <text string="Compression">Compresión</text>
  <text string="Options &amp; Info">GUI</text>
  <text string="This project takes a lot of time. ">Este proyecto necesita mucho trabajo. </text>
  <text string="Support it by donating.">Puedes contribuir con el proyecto realizando una donación.</text>
  <text string="Click the images to ">Clica en las imágenes para </text>
  <text string="donate.">contribuir.</text>
  <text string="Tell us what you think!">¡Cuentanos lo que piensas!</text>
  <text string="Give feedback by clicking here">Deja un comentario clicando aquí</text>
  <text string="Application Settings">Configuración de la aplicación</text>
  <text string="Reset all settings">Restaurar la configuración de BukkitGUI</text>
  <text string="Check for updates on startup">Comprobar actualizaciones al iniciar BukkitGUI</text>
  <text string="You might need to restart the GUI, in order for ">Es posible que debas reiniciar BukkitGUI, para que </text>
  <text string="these settings to take full eff">se apliquen los cambios</text>
  <text string="ect.">.</text>
  <text string="Tabpages:">Mostrar:</text>
  <text string="Show server options tab">Pestaña Configuración</text>
  <text string="Show plugins tab">Pestaña Plugins</text>
  <text string="Show task manager tab">Pestaña Tareas</text>
  <text string="Show error logging tab">Pestaña Log de Errores</text>
  <text string="Show players tab">Pestaña Jugadores</text>
  <text string="Config location:">Config. en:</text>
  <text string="Run server when GUI starts">Inicia el servidor al iniciar BukkitGUI</text>
  <text string="Start the server when the GUI starts, using the settings from the SuperStart tab.">Inicia el servidor cuando se inicia GUI, usando la configuración de la pestaña Inicio.</text>
  <text string="Toggle GUI autostart with windows">Ejecutar BukkitGUI al iniciar Windows</text>
  <text string="Toggle the GUI start when the user logs on. Administrator privileges required.">Ejecutar automáticamente GUI cuando se inicia Windows. Es necesario permisos de administrador.</text>
  <text string="Language:">Idioma:</text>
  <text string="Set the language for the GUI.">Selecciona el idioma de BukkitGUI.</text>
  <text string="Sound settings">Configuración de avisos acústicos</text>
  <text string="Play sound on severe message">Emitir sonido al producirse un error grave</text>
  <text string="Play a sound when the server sends a severe message">Emitir un sonido cuando el servidor genere avisos graves</text>
  <text string="Play sound on warning message">Emitir sonido al recibir advertencias</text>
  <text string="Play a sound when the server sends a warning">Emitir un sonido cuando el servidor genere mensajes de advertencia</text>
  <text string="Play sound on player leave">Emitir sonido al desconectarse un jugador</text>
  <text string="Play a sound when a player leaves the server">Emitir un sonido cuando los jugadores se desconectan del servidor</text>
  <text string="Play sound on player join">Emitir sonido al conectarse un jugador</text>
  <text string="Play a sound when a player connects to the server">Emitir un sonido cuando un jugador se conecta al servidor</text>
  <text string="Tray and sound">Barra de Tareas</text>
  <text string="On warning">Avisar las Advertencias</text>
  <text string="Show a tray balloon when the server throws a warning message">Muestra una viñeta cuando el servidor genera un mensaje de advertencia</text>
  <text string="On player leave">Avisar cuando se desconectan jugadores</text>
  <text string="Show a tray balloon when a player leaves.">Muestra una viñeta cuando un jugador se desconecta del servidor.</text>
  <text string="On player join">Avisar cuando se conectan jugadores</text>
  <text string="Show a tray balloon when a player joins.">Muestra una viñeta cuando un jugador se conecta al servidor.</text>
  <text string="On severe">Avisar errores graves</text>
  <text string="Show a tray balloon when the server throws a severe message">Muestra una viñeta cuando el servidor genera un advertencia grave</text>
  <text string="Always show balloons">Mostrar siempre las viñetas</text>
  <text string="Minimize to tray">Minimizar BukkitGUI en la Barra de Tareas</text>
  <text string="Minimize the GUI to tray when the minimize button is clicked.">Minimizar BukkitGUI en la Barra de Tareas cuando se clica en el botón minimizar.</text>
  <text string="Text output">Texto de salida</text>
  <text string="font preview">Esto es una prueba de texto</text>
  <text string="Font size:">Tamaño :</text>
  <text string="Font :">Fuente :</text>
  <text string="The font size that will be used for most lists and textboxes.">La fuente de texto que se usará para las listas y los cuadros de texto.</text>
  <text string="Font preview:">Vista previa del texto:</text>
  <text string="Unknown :">Desconocido :</text>
  <text string="[SEVERE] :">[GRAVE] :</text>
  <text string="[WARNING] :">[AVDERTENCIA] :</text>
  <text string="Player event :">Jugador :</text>
  <text string="[INFO] :">[INFO] :</text>
  <text string="Show date">Mostrar Fecha</text>
  <text string="Show time">Mostrar Hora</text>
  <text string="Computer Info">Información del Sistema</text>
  <text string="Computer Name:">Nombre:</text>
  <text string="About">A cerca de</text>
  <text string="Open Updater">Abrir Actualizador de BukkitGUI</text>
  <text string="BukkitGUI">BukkitGUI</text>
  <text string="Exit">Salir</text>
  <text string="The following xml file could not be loaded. Please check for errors">El siguiente archivo xml no se ha podido cargar. Por favor comprueba los errores</text>
  <text string="Invalid XML file">Archivo XML no válido</text>
  <text string="Oh no! something went wrong in the application. The application is unable to continue it's work, and will exit. Please report this error to the developers">
    ¡Oh no! Algo funciona mal en la aplicación. La aplicación no puede continuar con su trabajo, y se cerrará. Por favor informa de este error a los desarrolladores
  </text>
  <text string="Critical error">Error crítico</text>
  <text string="This file is too big to send using the error report. If you want to report it, please upload %appdata%/Bertware/BukkitGUI/Logging/BukkitGUI.xlog and send it to contact@bertware.net">
    Este archivo es demasiado grande para enviarlo por el sistema de Informes de errores. Si quieres informar, por favor dirígete a %appdata%/Bertware/BukkitGUI/Logging/BukkitGUI.xlog y envía el archivo a contact@bertware.net
  </text>
  <text string="file too big">archivo demasiado grande</text>
  <text string="Can't send bug report: no internet available">No se puede enviar el informe: no hay conexión a Internet</text>
  <text string="Can't send log">No se puede enviar el log</text>
  <text string=", ">, </text>
  <text string="Update information invalid: server returned error">Información de actualización inválida: el servidor a devuelto un error</text>
  <text string="Please contact the developers">Por favor contacta con el desarrollador</text>
  <text string="Server returned error">El servidor a devuelto un error</text>
  <text string="One of your backup profiles wasn't loaded: the file is probably corrupt! The backup profile was removed.">
    Uno de los perfiles de restauración no se pueden cargar: probablemente el archivo esté corrupto! El perfil de restauración será eliminado.
  </text>
  <text string="Can't load backup profile">No se puede cargar el perfil de restauración</text>
  <text string="This file couldn't be created:">El siguiente archivo no se puede crear:</text>
  <text string="Couldn't create file">No se puede crear el archivo</text>
  <text string="The current bukkit version could not be determined. It seems like you don't have permissions to do this. Try running the GUI as administator">
    No se puede determinar la versión actual de Bukkit. Parece que GUI no tiene permisos para recoger esta información. Intenta ejecutar GUI como administrador.
  </text>
  <text string="Insufficient rights">Permisos Insuficientes</text>
  <text string="The downloaded file could not be saved. Are you allowed to write to this location?">El archivo descargado no se ha guardado. Seguro que se puede escribir en esta localización?</text>
  <text string="Couldn't save file">No se ha guardado el archivo</text>
  <text string="Plugin">Plugin</text>
  <text string="Current Version">Versión Actual</text>
  <text string="New version">Nueva Versión</text>
  <text string="Bukkit Version">Versión de Bukkit</text>
  <text string="Status: Idle">Estado: Óptimo</text>
  <text string="Update!">Actualizado!</text>
  <text string="Force update if already up to date">Forzar actualización</text>
  <text string="Update for bukkit build:">Actualización para Bukkit build:</text>
  <text string="Check all">Comprobar todo</text>
  <text string="Update plugins">Actualizar plugins</text>
  <text string="Loading plugin data:">Cargando datos del plugin:</text>
  <text string="Loading plugin data to screen...">Cargando datos del plugin en la pantalla...</text>
  <text string="No data available">No hay datos disponibles</text>
  <text string="No downloads available">No hay descargas disponibles</text>
  <text string="Idle">Reposo</text>
  <text string="Updating plugin">Actualizando plugin</text>
  <text string="to version">a la versión</text>
  <text string="Skipping plugin">Omitiendo plugin</text>
  <text string="cannot update">no actualizable</text>
  <text string="server output">salida del servidor</text>
  <text string="kickall">Kikear a Todos</text>
  <text string="close gui">cerrar GUI</text>
  <text string="Run this task when certain text is received from the server. Warning! this might be CPU intensive!">Ejecutar esta tarea cuando se reciba un determinado texto del servidor. Atención! esto puede cargar mucho la CPU!</text>
  <text string="the text that will trigger this. Note: if this text is CONTAINED in the server text, the event will run.">
    el texto que va a ejecutar esto. Nota: si el texto está CONTENIDO en el texto del servidor, el evento se ejecutará.
  </text>
  <text string="Kick all the players that are online.">Expulsa a todos los jugadores del servidor.</text>
  <text string="Optional: the reason for kicking them. (if you have a plugin that supports kick reasons)">Opcional: la razón de la expulsión. (si tienes un plugin que soporte razones de expulsión)</text>
  <text string="Close the GUI.">Cerrar BukkitGUI.</text>
  <text string="The server could not be started. It seems like you don't have permissions to do this. Try running the GUI as administator">
    El servidor no se puede iniciar. Es posible que no tengas permisos. Intenta ejecutar BukkitGUI como administrador.
  </text>
  <text string="Error">Error</text>
  <text string="Right click for options, double click for details. Ctrl+click or Shift+click to select multiple items.">Botón derecho para mostrar las opciones, doble clic para obtener detalles. Ctrl+clic o Mayús+clic para seleccionar más elementos.</text>
  <text string="Test">Prueba</text>
  <text string="Right click for options, double click for details. Ctrl+click or Shift+click to s">Botón derecho para mostrar las opciones, doble clic para obtener detalles. Ctrl+clic o Mayús+clic para </text>
  <text string="elect multiple items.">seleccionar más elementos.</text>
  <text string="Updated">Actualizado</text>
  <text string="Adventure">Aventura</text>
  <text string="This file is too big to send using the error report. If you want to report it, please upload %appdata%/Bertware/BukkitGUI/Logging/BukkitGUI.log and send it to contact@bertware.net">
    Este archivo es demasiado grande como para enviarlo como reporte de errores. Si quieres reportarlo, por favor coge el archivo %appdata%/Bertware/BukkitGUI/Logging/BukkitGUI.log y envíalo a contact@bertware.net
  </text>
  <text string="The update couldn't be downloaded. The update URL is invalid. Try updating manually.">La actualización no se puede descargar. La ruta URL de descarga es incorrecta. Prueba a descargarla manualmente.</text>
  <text string="Error while updating">Error durante la actualización</text>
  <text string="The update couldn't be installed. It seems like you don't have permissions to do this. Try running the GUI as administator, or install the update manually.">
    La actualización no se ha instalado. Parece ser que no tienes permisos para hacer esto. Intenta ejecutar BukkitGUI como administrador, o instala la actualización manualmente.
  </text>
  <text string="Enable task">Activar tarea</text>
  <text string="These changes will take effect the next time you start the GUI">Estos cambios surtirán efecto la próxima vez que se inicie BukkitGUI</text>
  <text string="The backup can't be performed: the following drive could not be found. Is this a removeable device (e.g. USB stick)">
    No se puede realizar la copia de seguridad: no se encuentra la ruta. Puede que sea una unidad extraible (ej. un PenDrive)
  </text>
  <text string="Drive not found">No se ha encontrado la ruta</text>
  <text string="An error occured while creating a backup for the following backup scheme:">A ocurrido un error cuando se creaba la copia de seguridad:</text>
  <text string="The backup might be incomplete or corrupt. Make sure all task settings are valid. The error has been logged">
    La copia de seguridad es incompleta o corrupta. Asegúrate que todas las tareas sean correctas. El error se ha registrado correctamente
  </text>
  <text string="Backup failed">Copia de Seguridad errónea</text>
  <text string="Couldn't find plugin!">No se encuentra el plugin!</text>
  <text string="Please write your feedback in English.">Por favor escribe el comentario en Inglés.</text>
  <text string="File download failed!">Descarga del archivo errónea!</text>
  <text string="Download failed!">Descarga errónea!</text>
  <text string="The downloaded file could not be saved. Are you allowed to write to this location? Try running as administrator">
    El archivo descargado no se a guardado. ¿Tienes permisos de escritura esta ruta? Intenta ejecutarlo como administrador
  </text>
  <text string="You will now be redirected to a 3rd party website that is not owned by Bertware.">Ahora serás redirigido a una web de terceros que no es propiedad de Bertware.</text>
  <text string="Redirect">Redirecionar</text>
  <text string="Description:">Descripción:</text>
  <text string="Task failed:">Tarea errónea:</text>
  <text string="Could not execute shell command:">No se puede ejecutar el comando shell:</text>
  <text string="Is this a valid task?">¿Es una tarea correcta?</text>
  <text string="Task failed">Tarea errónea</text>
  <text string="The taskmanager couldn't execute this task:">El gestor de tareas no puede ejecutar esta tarea:</text>
  <text string="Couldn't get the backup settings for backup scheme">No se puede obtener la copia de seguridad de la configuración</text>
  <text string="Task failed!">Tarea errónea!</text>
  <text string="&amp;Kill">&amp;Forzar</text>
  <text string="The server could not be started. It seems like you don't have permissions to access needed files. Try running the GUI as administator">
    No se puede iniciar el servidor. Es posible que no se pueda acceder a los archivos. Intenta ejecutar BukkitGUI como administrador.
  </text>
  <text string="File I/O error">Error I/O de archivo</text>
  <text string="Killed remote server connection due to an error in remote reader thread.">Forzar el cierre de la conexión remota puede producir errores.</text>
  <text string="Clear output">Limpiar log</text>
  <text string="Download #">Descargar #</text>
  <text string="Auto-update when an update is available">Auto-actualizar cuando exista una actualización disponible</text>
  <text string="Show a dialog that prompts to update when an update is available. Note: the serve">Mostrar un aviso antes de actualizar. Nota: el servidor</text>
  <text string="r won't start until the dialog has been closed. ">no se iniciará hasta cerrar el aviso. </text>
  <text string="This option can't be combined ">Esta opción no permite ser combinada </text>
  <text string="with the auto-update feature">con la característica de auto-actualizar</text>
  <text string="Copy">Copiar</text>
  <text string="Copy the selected items to your clipboard">Copiar los elementos seleccionados al portapapeles</text>
  <text string="Enabled">Activado</text>
  <text string="Loading...">Cargando...</text>
  <text string="Load on startup">Cargar al iniciar</text>
  <text string="Load the plugin list when the server starts. This list is +- 2Mb.">Cargar la lista de plugins al iniciar el servidor. La lista ocupa +- 2Mb.</text>
  <text string="Otherwise the ">De lo contrario la </text>
  <text string="plugin list will only be loaded when visiting this tab">lista de plugins solo será cargada visitando esta pestaña</text>
  <text string="nosort">nosort</text>
  <text string="Set custom slug...">Configurar slug...</text>
  <text string="Open folder...">Abrir carpeta...</text>
  <text string="Run in light mode">Ejecutar en modo básico</text>
  <text string="Run GUI when windows starts">Ejecutar BukkitGUI al iniciar Windows</text>
  <text string="WARNING: No craftbukkit file selected, bukkit version can't be determined. Auto update check cancelled.">
    ATENCIÓN: No hay ningún archivo de CraftBukkit seleccionado y no se puede determinar la versión de Bukkit. La Auto-actualización ha sido cancelada.
  </text>
  <text string="WARNING: Turn of ">ATENCIÓN: Cámbialo </text>
  <text string="WARNING: or make sure the .jar file contains bukkit">ATENCIÓN: o asegúrate de que el archivo .jar corresponda a Bukkit</text>
  <text string="Stopping the server...">Parando el servidor...</text>
  <text string="Stopping server">Parando servidor</text>
  <text string="Restarting the server...">Reiniciando el servidor...</text>
  <text string="Reloading the server...">Recargando el servidor...</text>
  <text string="The server is starting...">Iniciando el servidor...</text>
  <text string="Server started...">Iniciando servidor...</text>
  <text string="Clear all text">Elimina todo el texto</text>
  <text string="00:00:00">00:00:00</text>
  <text string="UTF-8 compatibility mode">Compatible con UTF-8</text>
  <text string="Enable this if you need to read chinese (or other UTF-8) text from the server out">¡ATENCIÓN NO ACTIVAR! Solo se debe activar si el servidor necesita leer o</text>
  <text string="put, or need to write chinese (or other UTF-8) text to the server input.">escribir en chino (o en otro tipo de texto UTF-8).</text>
  <text string="000% [00000MB]">000 [00000MB]</text>
  <text string="This project takes a lot of time. &#xD;&#xA;Support it by donating.&#xD;&#xA;Click the images to ">
    Este proyecto necesita mucho tiempo y esfuerzo.
    Ayúdanos realizando una donación.
    Clica en la imagen de
  </text>
  <text string="Tell us what you think!&#xD;&#xA;Give feedback by clicking here">
    ¡Comenta lo que te parece!
    Envía tus sugerencias clicando aquí.
  </text>
  <text string="You might need to restart the GUI, in order for &#xD;&#xA;these settings to take full eff">
    Para aplicar los cambios realizados más abajo
    es necesario reiniciar la aplicación.
  </text>
  <text string="Iniciando servidor">Iniciando servidor</text>
  <text string="Servidor iniciado">Servidor iniciado</text>
  <text string="Parando servidor">Parando servidor</text>
  <text string="Servidor detenido">Servidor detenido</text>
  <text string="Support us and say thanks: donate (paypal)">Ayúdanos donando en PayPal</text>
  <text string="Download Latest Beta Build">Descargar la última Beta</text>
  <text string="Search!">Buscar!</text>
  <text string="or browse a category:">o buscar en una categoría</text>
  <text string="Search:">Buscar:</text>
  <text string="Clear">Limpiar</text>
  <text string="Browse output">Explorar</text>
  <text string="Browse console output">Buscar en la Consola</text>
  <text string="Unknown">Desconocido</text>
  <text string="Set-up port forwarding...">Configuración de puertos...</text>
  <text string="00%">00%25</text>
  <text string="Set-up port forwarding... (experimental)">Configurar Redirección de Puertos... (experimental)</text>
  <text string="BukkitGui v2 is available! visit get.bertware.net">¡BukkitGui v2 está disponible en get.bertware.net!</text>
  <text string="Ignored">Ignorar</text>
</language>